{
  "feedback": [
    {
      "rating": 3,
      "text": "hey",
      "id": 1
    },
    {
      "rating": 4,
      "text": "hi",
      "id": 2
    },
    {
      "rating": 5,
      "text": "hello",
      "id": 3
    },
    {
      "rating": 2,
      "text": "hey",
      "id": 4
    },
    {
      "rating": 1,
      "text": "hi",
      "id": 5
    },
    {
      "rating": 3,
      "text": "hello",
      "id": 6
    },
    {
      "rating": 4,
      "text": "hey",
      "id": 7
    },
    {
      "rating": 5,
      "text": "hi",
      "id": 8
    },
    {
      "rating": 2,
      "text": "hello",
      "id": 9
    },
    {
      "rating": 1,
      "text": "hey",
      "id": 10
    },
    {
      "rating": 4,
      "text": "hiiiiiiiiiiiii",
      "id": 11
    },
    {
      "rating": 3,
      "text": "i get corrected",
      "id": 12
    }
  ]
}